byugrid.py
byugrid-0.1.2.dist-info/LICENSE
byugrid-0.1.2.dist-info/WHEEL
byugrid-0.1.2.dist-info/METADATA
byugrid-0.1.2.dist-info/RECORD
